tcp_proxy_server/__init__.py
tcp_proxy_server/handlers.py
tcp_proxy_server/multisocket.py
tcp_proxy_server-0.0.4.dist-info/LICENSE
tcp_proxy_server-0.0.4.dist-info/METADATA
tcp_proxy_server-0.0.4.dist-info/WHEEL
tcp_proxy_server-0.0.4.dist-info/top_level.txt
tcp_proxy_server-0.0.4.dist-info/RECORD
