Metadata-Version: 2.1
Name: tcp-proxy-server
Version: 0.0.4
Summary: tcp proxy server to intercept tcp
Home-page: https://github.com/ssh-mitm/tcp-proxy-server
Author: SSH-MITM Dev-Team
Author-email: support@ssh-mitm.at
License: UNKNOWN
Platform: UNKNOWN
Classifier: Programming Language :: Python :: 3
Classifier: Programming Language :: Python :: 3.6
Classifier: Programming Language :: Python :: 3.7
Classifier: Programming Language :: Python :: 3.8
Classifier: License :: OSI Approved :: GNU Lesser General Public License v3 (LGPLv3)
Classifier: Topic :: System :: Networking
Requires-Python: >= 3.6
